{"date": "2026-07-23", "카카오선물하기": [{"rank": 1, "category": "멀티비타민/종합비타민", "name": "독일 명품 비타민 오쏘몰 이뮨 멀티비타민&미네랄 8입(7+1) - 단독 기프트박스 증정 (공식수입)", "brand": "오쏘몰", "price": "34,000원", "url": "https://gift.kakao.com/product/2301047", "image": "https://st.kakaocdn.net/product/gift/product/20260720083745_3a4cff6bdbb44f4e9cecf5e36eabe528.jpg", "badge": "same"}, {"rank": 2, "category": "멀티비타민/종합비타민", "name": "한국인 맞춤 비타민 옵티젠 이뮨 멀티비타민&미네랄 10입 / 1박스 (+GIFT 쇼핑백)", "brand": "옵티젠", "price": "26,900원", "url": "https://gift.kakao.com/product/7608679", "image": "https://st.kakaocdn.net/product/gift/product/20260703114353_3ee4124918ae4776af8a6954e0a43f76.jpg", "badge": "same"}, {"rank": 3, "category": "멀티비타민/종합비타민", "name": "독일 명품 비타민 오쏘몰 이뮨 멀티비타민&미네랄 30입 - 시그니처 기프트 에디션 (공식수입)", "brand": "오쏘몰", "price": "109,000원", "url": "https://gift.kakao.com/product/2484405", "image": "https://st.kakaocdn.net/product/gift/product/20260718112704_e8942030fa4b4fee80048cf5f99aba09.jpg", "badge": "same"}, {"rank": 4, "category": "멀티비타민/종합비타민", "name": "독일 명품 비타민 오쏘몰 이뮨 멀티비타민&미네랄 10입 - 슬리브 기프트 에디션 (공식수입)", "brand": "오쏘몰", "price": "45,000원", "url": "https://gift.kakao.com/product/11866425", "image": "https://st.kakaocdn.net/product/gift/product/20260715133556_5b220cca6be34a0aa6491af5bca27f47.jpg", "badge": "same"}, {"rank": 5, "category": "멀티비타민/종합비타민", "name": "명품 비타민 뉴트리포유 듀얼+ 이뮨 종합 멀티비타민&미네랄 7입+2입 증정 - 선물하기 단독 에디션", "brand": "뉴트리포유", "price": "19,900원", "url": "https://gift.kakao.com/product/10056171", "image": "https://st.kakaocdn.net/product/gift/product/20260219100848_1c2cc8073bd44eaab9f09d6b8fb8f34c.jpg", "badge": "same"}, {"rank": 6, "category": "홍삼/인삼", "name": "신상비타민선물 [정관장] 활기마이트(액상30ml+분말500mg) 7입 + [증정] 1입", "brand": "정관장", "price": "35,000원", "url": "https://gift.kakao.com/product/12159594", "image": "https://st.kakaocdn.net/product/gift/product/20260629110109_f83c124733904b58826d6a7caacb4073.jpg", "badge": "same"}, {"rank": 7, "category": "멀티비타민/종합비타민", "name": "[리뷰이벤트/센트룸] 맛있는 멀티비타민 미네랄 멀티구미 (80구미)", "brand": "센트룸", "price": "24,000원", "url": "https://gift.kakao.com/product/7320451", "image": "https://st.kakaocdn.net/product/gift/product/20260720092938_9626171b4b1241379bcc67bbdab37930.jpg", "badge": "same"}, {"rank": 8, "category": "기타/특수목적", "name": "성별 맞춤 설계 오쏘몰 바이탈 m/f 남성/여성 선택가능 14입 - 시그니처 기프트 에디션 (공식수입)", "brand": "오쏘몰", "price": "59,800원", "url": "https://gift.kakao.com/product/8167919", "image": "https://st.kakaocdn.net/product/gift/product/20260720085358_f71eba17fe274d1586a7ac1b6ebd74fb.jpg", "badge": "same"}, {"rank": 9, "category": "멀티비타민/종합비타민", "name": "비타민 선물 추천 아임비타 멀티비타민 이뮨샷 1박스(5입) / 비타민선물 응원선물 에너지 선물 직장동료 선물", "brand": "종근당건강", "price": "15,900원", "url": "https://gift.kakao.com/product/5551542", "image": "https://st.kakaocdn.net/product/gift/product/20260513082713_f5025425b9024348b2621639f67a34af.jpg", "badge": "same"}, {"rank": 10, "category": "멀티비타민/종합비타민", "name": "\"올인원 명품비타민\" 이뮨비타민 올인원 멀티비타민&미네랄 프로 30병+쇼핑백증정", "brand": "닥터블릿", "price": "52,900원", "url": "https://gift.kakao.com/product/10903147", "image": "https://st.kakaocdn.net/product/gift/product/20260601193534_8d89165f65364cb0b3c77a98481c17d6.jpg", "badge": "same"}], "다이소몰": [{"rank": 1, "category": "루테인/눈건강", "name": "대웅제약 식물성 뉴티지 오메가3 30캡슐 30일분", "brand": "대웅제약", "price": "5,000원", "url": "https://www.daisomall.co.kr/pd/pdr/SCR_PDR_0001?pdNo=600000203&recmYn=N", "image": "https://cdn.daisomall.co.kr/file/PD/20251202/7FdyxsWTlcbRJnDROGoC600000203_00_007FdyxsWTlcbRJnDROGoC.jpg", "badge": "new"}, {"rank": 2, "category": "기타/특수목적", "name": "동국 맛있는 센시안 브이캔디 20정 20일분", "brand": "동국제약", "price": "3,000원", "url": "https://www.daisomall.co.kr/pd/pdr/SCR_PDR_0001?pdNo=610910968&recmYn=N", "image": "https://cdn.daisomall.co.kr/file/PD/20260409/2cHZmOZUJJcZL1ip2bls610910968_00_002cHZmOZUJJcZL1ip2bls.png", "badge": "up:4"}, {"rank": 3, "category": "마그네슘", "name": "자연관 리프레쉬 마그네슘＆L-테아닌 4병 4일분", "brand": "자연관", "price": "5,000원", "url": "https://www.daisomall.co.kr/pd/pdr/SCR_PDR_0001?pdNo=032627142&recmYn=N", "image": "https://cdn.daisomall.co.kr/file/PD/20260612/IiBr1SI0rlUycwbkaeGq032627142_00_01IiBr1SI0rlUycwbkaeGq.jpg", "badge": "new"}, {"rank": 4, "category": "기타/특수목적", "name": "대웅제약 쏘팔메토 옥타코사놀 30캡슐 30일분", "brand": "대웅제약", "price": "5,000원", "url": "https://www.daisomall.co.kr/pd/pdr/SCR_PDR_0001?pdNo=600000139&recmYn=N", "image": "https://cdn.daisomall.co.kr/file/PD/20250408/Am2C7Da2wracg1TigkAF600000139_00_00Am2C7Da2wracg1TigkAF.png", "badge": "new"}, {"rank": 5, "category": "기타/특수목적", "name": "홀베리 유기농 레몬자몽즙 10포", "brand": "홀베리", "price": "5,000원", "url": "https://www.daisomall.co.kr/pd/pdr/SCR_PDR_0001?pdNo=965923433&recmYn=N", "image": "https://cdn.daisomall.co.kr/file/PD/20260305/0r6Ta1PlJSrc27DsREL6965923433_00_000r6Ta1PlJSrc27DsREL6.jpg", "badge": "new"}, {"rank": 6, "category": "루테인/눈건강", "name": "종근당건강 눈건강엔 루테인지아잔틴", "brand": "종근당건강", "price": "5,000원", "url": "https://www.daisomall.co.kr/pd/pdr/SCR_PDR_0001?pdNo=591580541&recmYn=N", "image": "https://cdn.daisomall.co.kr/file/PD/20250430/yuK2zGjcuX8RmMDP9k9P591580541_00_00yuK2zGjcuX8RmMDP9k9P.jpg", "badge": "new"}, {"rank": 7, "category": "마그네슘", "name": "대웅제약 마그네슘 10정 10일분", "brand": "대웅제약", "price": "1,000원", "url": "https://www.daisomall.co.kr/pd/pdr/SCR_PDR_0001?pdNo=600000270&recmYn=N", "image": "https://cdn.daisomall.co.kr/file/PD/20260504/rjUOcdF4xff4PIy7VUYT600000270_00_01rjUOcdF4xff4PIy7VUYT.png", "badge": "new"}, {"rank": 8, "category": "기타/특수목적", "name": "락피도 티니핑 철분스틱 12포 12일분", "brand": "락피도", "price": "5,000원", "url": "https://www.daisomall.co.kr/pd/pdr/SCR_PDR_0001?pdNo=951817120&recmYn=N", "image": "https://cdn.daisomall.co.kr/file/PD/20260226/Lb8S1LqMvpkz0uUPx4SJ951817120_00_01Lb8S1LqMvpkz0uUPx4SJ.jpg", "badge": "new"}, {"rank": 9, "category": "기타/특수목적", "name": "홀베리 유기농 엑스트라버진 올리브유 10포", "brand": "홀베리", "price": "5,000원", "url": "https://www.daisomall.co.kr/pd/pdr/SCR_PDR_0001?pdNo=032640075&recmYn=N", "image": "https://cdn.daisomall.co.kr/file/PD/20260312/0RECqyOK2V8qTztn2K7E032640075_00_000RECqyOK2V8qTztn2K7E.jpg", "badge": "new"}, {"rank": 10, "category": "다이어트/체중관리", "name": "대웅제약 바나바잎 추출물 30정 (30일분)", "brand": "대웅제약", "price": "3,000원", "url": "https://www.daisomall.co.kr/pd/pdr/SCR_PDR_0001?pdNo=600000131&recmYn=N", "image": "https://cdn.daisomall.co.kr/file/PD/20250408/rCiQaBH4VQ1rKKr7rz83600000131_00_00rCiQaBH4VQ1rKKr7rz83.png", "badge": "new"}], "올리브영": [{"rank": 1, "category": "기타/특수목적", "name": "[7월 올영픽/1일 1정] 바이탈뷰티 메타그린 슬림업 30일 (+15일)", "brand": "바이탈뷰티", "price": "24,900원", "url": "https://www.oliveyoung.co.kr/store/goods/getGoodsDetail.do?goodsNo=A000000248462&dispCatNo=90000010009&trackingCd=Best_Sellingbest&t_page=%EB%9E%AD%ED%82%B9&t_click=%ED%8C%90%EB%A7%A4%EB%9E%AD%ED%82%B9_%EA%B1%B4%EA%B0%95%EC%8B%9D%ED%92%88_%EC%83%81%ED%92%88%EC%83%81%EC%84%B8&t_number=1", "image": "https://image.oliveyoung.co.kr/cfimages/cf-goods/uploads/images/thumbnails/400/10/0000/0024/A00000024846224ko.jpg?l=ko", "badge": "up:6"}, {"rank": 2, "category": "기타/특수목적", "name": "[곽민경 PICK] 생활약속 기분전환 알파플러스/오리지널 10포 (+1포 증정기획)", "brand": "생활약속", "price": "13,000원", "url": "https://www.oliveyoung.co.kr/store/goods/getGoodsDetail.do?goodsNo=A000000180121&dispCatNo=90000010009&trackingCd=Best_Sellingbest&t_page=%EB%9E%AD%ED%82%B9&t_click=%ED%8C%90%EB%A7%A4%EB%9E%AD%ED%82%B9_%EA%B1%B4%EA%B0%95%EC%8B%9D%ED%92%88_%EC%83%81%ED%92%88%EC%83%81%EC%84%B8&t_number=2", "image": "https://image.oliveyoung.co.kr/cfimages/cf-goods/uploads/images/thumbnails/400/10/0000/0018/A00000018012129ko.png?l=ko", "badge": "new"}, {"rank": 3, "category": "비타민C/항산화", "name": "고려은단 비타민C1000 600정 (20개월분)", "brand": "고려은단", "price": "42,900원", "url": "https://www.oliveyoung.co.kr/store/goods/getGoodsDetail.do?goodsNo=A000000225938&dispCatNo=90000010009&trackingCd=Best_Sellingbest&t_page=%EB%9E%AD%ED%82%B9&t_click=%ED%8C%90%EB%A7%A4%EB%9E%AD%ED%82%B9_%EA%B1%B4%EA%B0%95%EC%8B%9D%ED%92%88_%EC%83%81%ED%92%88%EC%83%81%EC%84%B8&t_number=3", "image": "https://image.oliveyoung.co.kr/cfimages/cf-goods/uploads/images/thumbnails/400/10/0000/0022/A00000022593803ko.jpg?l=ko", "badge": "down:2"}, {"rank": 4, "category": "다이어트/체중관리", "name": "[7월 올영픽/다이어트 부스터] 바이탈뷰티 메타그린 부스터샷 7 (+1)개입", "brand": "바이탈뷰티", "price": "19,400원", "url": "https://www.oliveyoung.co.kr/store/goods/getGoodsDetail.do?goodsNo=A000000241581&dispCatNo=90000010009&trackingCd=Best_Sellingbest&t_page=%EB%9E%AD%ED%82%B9&t_click=%ED%8C%90%EB%A7%A4%EB%9E%AD%ED%82%B9_%EA%B1%B4%EA%B0%95%EC%8B%9D%ED%92%88_%EC%83%81%ED%92%88%EC%83%81%EC%84%B8&t_number=4", "image": "https://image.oliveyoung.co.kr/cfimages/cf-goods/uploads/images/thumbnails/400/10/0000/0024/A00000024158158ko.jpg?l=ko", "badge": "new"}, {"rank": 5, "category": "멀티비타민/종합비타민", "name": "오쏘몰 이뮨 멀티비타민&미네랄 14입", "brand": "오쏘몰", "price": "55,900원", "url": "https://www.oliveyoung.co.kr/store/goods/getGoodsDetail.do?goodsNo=A000000193086&dispCatNo=90000010009&trackingCd=Best_Sellingbest&t_page=%EB%9E%AD%ED%82%B9&t_click=%ED%8C%90%EB%A7%A4%EB%9E%AD%ED%82%B9_%EA%B1%B4%EA%B0%95%EC%8B%9D%ED%92%88_%EC%83%81%ED%92%88%EC%83%81%EC%84%B8&t_number=5", "image": "https://image.oliveyoung.co.kr/cfimages/cf-goods/uploads/images/thumbnails/400/10/0000/0019/A00000019308648ko.jpg?l=ko", "badge": "up:4"}, {"rank": 6, "category": "다이어트/체중관리", "name": "프로뉴트리션 듀얼플랜 다이어트 유산균 14포", "brand": "프로뉴트리션", "price": "35,800원", "url": "https://www.oliveyoung.co.kr/store/goods/getGoodsDetail.do?goodsNo=A000000205496&dispCatNo=90000010009&trackingCd=Best_Sellingbest&t_page=%EB%9E%AD%ED%82%B9&t_click=%ED%8C%90%EB%A7%A4%EB%9E%AD%ED%82%B9_%EA%B1%B4%EA%B0%95%EC%8B%9D%ED%92%88_%EC%83%81%ED%92%88%EC%83%81%EC%84%B8&t_number=6", "image": "https://image.oliveyoung.co.kr/cfimages/cf-goods/uploads/images/thumbnails/400/10/0000/0020/A00000020549614ko.jpg?l=ko", "badge": "down:2"}, {"rank": 7, "category": "프로바이오틱스/유산균", "name": "[덴프스] 덴마크 유산균이야기 우먼 2개월분(질유산균) + 철분 헤모케어 3포 증정", "brand": "덴프스", "price": "39,000원", "url": "https://www.oliveyoung.co.kr/store/goods/getGoodsDetail.do?goodsNo=A000000202658&dispCatNo=90000010009&trackingCd=Best_Sellingbest&t_page=%EB%9E%AD%ED%82%B9&t_click=%ED%8C%90%EB%A7%A4%EB%9E%AD%ED%82%B9_%EA%B1%B4%EA%B0%95%EC%8B%9D%ED%92%88_%EC%83%81%ED%92%88%EC%83%81%EC%84%B8&t_number=7", "image": "https://image.oliveyoung.co.kr/cfimages/cf-goods/uploads/images/thumbnails/400/10/0000/0020/A00000020265829ko.jpg?l=ko", "badge": "up:3"}, {"rank": 8, "category": "기타/특수목적", "name": "[추성훈PICK] 헬스헬퍼 맥스컷 프로 크롬 60캡슐 (10일분)", "brand": "헬스헬퍼", "price": "17,200원", "url": "https://www.oliveyoung.co.kr/store/goods/getGoodsDetail.do?goodsNo=A000000237482&dispCatNo=90000010009&trackingCd=Best_Sellingbest&t_page=%EB%9E%AD%ED%82%B9&t_click=%ED%8C%90%EB%A7%A4%EB%9E%AD%ED%82%B9_%EA%B1%B4%EA%B0%95%EC%8B%9D%ED%92%88_%EC%83%81%ED%92%88%EC%83%81%EC%84%B8&t_number=8", "image": "https://image.oliveyoung.co.kr/cfimages/cf-goods/uploads/images/thumbnails/400/10/0000/0023/A00000023748209ko.jpg?l=ko", "badge": "new"}, {"rank": 9, "category": "비타민C/항산화", "name": "고려은단 메가도스C 비타민C 3000mg 100포 (100일분)", "brand": "고려은단", "price": "25,900원", "url": "https://www.oliveyoung.co.kr/store/goods/getGoodsDetail.do?goodsNo=A000000225906&dispCatNo=90000010009&trackingCd=Best_Sellingbest&t_page=%EB%9E%AD%ED%82%B9&t_click=%ED%8C%90%EB%A7%A4%EB%9E%AD%ED%82%B9_%EA%B1%B4%EA%B0%95%EC%8B%9D%ED%92%88_%EC%83%81%ED%92%88%EC%83%81%EC%84%B8&t_number=9", "image": "https://image.oliveyoung.co.kr/cfimages/cf-goods/uploads/images/thumbnails/400/10/0000/0022/A00000022590605ko.jpg?l=ko", "badge": "new"}, {"rank": 10, "category": "기타/특수목적", "name": "[7월 올영픽/서현PICK] 콜레올로지 PRO 600mg*30(+10)/60정 단품", "brand": "푸드올로지", "price": "17,900원", "url": "https://www.oliveyoung.co.kr/store/goods/getGoodsDetail.do?goodsNo=A000000175634&dispCatNo=90000010009&trackingCd=Best_Sellingbest&t_page=%EB%9E%AD%ED%82%B9&t_click=%ED%8C%90%EB%A7%A4%EB%9E%AD%ED%82%B9_%EA%B1%B4%EA%B0%95%EC%8B%9D%ED%92%88_%EC%83%81%ED%92%88%EC%83%81%EC%84%B8&t_number=10", "image": "https://image.oliveyoung.co.kr/cfimages/cf-goods/uploads/images/thumbnails/400/10/0000/0017/A00000017563481ko.jpg?l=ko", "badge": "new"}]}